atml/__init__.py
atml/cat.py
atml/exp.py
atml/irt.py
atml/measure.py
atml/visualisation.py
at_ml-0.1.dist-info/LICENSE
at_ml-0.1.dist-info/METADATA
at_ml-0.1.dist-info/WHEEL
at_ml-0.1.dist-info/top_level.txt
at_ml-0.1.dist-info/RECORD
